{
  "stats": {
    "suites": 1,
    "tests": 2,
    "passes": 2,
    "pending": 0,
    "failures": 0,
    "start": "2021-03-15T08:31:43.837Z",
    "end": "2021-03-15T08:31:45.102Z",
    "duration": 1236,
    "testsRegistered": 2,
    "passPercent": 100,
    "pendingPercent": 0,
    "other": 0,
    "hasOther": false,
    "skipped": 0,
    "hasSkipped": false
  },
  "results": [
    {
      "uuid": "ffadacc7-6dc3-4933-a98e-3c313c46ecdf",
      "title": "",
      "fullFile": "cypress\\integration\\fetchDataAdvanced.spec.js",
      "file": "cypress\\integration\\fetchDataAdvanced.spec.js",
      "beforeHooks": [],
      "afterHooks": [],
      "tests": [],
      "suites": [
        {
          "uuid": "6a5c3ee5-2908-4884-b638-bc9d5f780a4b",
          "title": "Fetch phones app",
          "fullFile": "",
          "file": "",
          "beforeHooks": [],
          "afterHooks": [],
          "tests": [
            {
              "title": "should take an array of all successfully received details",
              "fullTitle": "Fetch phones app should take an array of all successfully received details",
              "timedOut": null,
              "duration": 846,
              "state": "passed",
              "speed": "slow",
              "pass": true,
              "fail": false,
              "pending": false,
              "context": null,
              "code": "cy.get('@all').contains('All Successful');",
              "err": {},
              "uuid": "bd42c36e-f3fb-431f-8158-dee43d36386d",
              "parentUUID": "6a5c3ee5-2908-4884-b638-bc9d5f780a4b",
              "isHook": false,
              "skipped": false
            },
            {
              "title": "should contain phones in all successful",
              "fullTitle": "Fetch phones app should contain phones in all successful",
              "timedOut": null,
              "duration": 390,
              "state": "passed",
              "speed": "slow",
              "pass": true,
              "fail": false,
              "pending": false,
              "context": null,
              "code": "cy.get('@all').contains('MOTOROLA-XOOM-WITH-WI-FI');\ncy.get('@all').contains('MOTOROLA-XOOM');\ncy.get('@all').contains('MOTOROLA-CHARM-WITH-MOTOBLUR');",
              "err": {},
              "uuid": "9073a53e-3f4c-4169-b97e-6c848d2a27b1",
              "parentUUID": "6a5c3ee5-2908-4884-b638-bc9d5f780a4b",
              "isHook": false,
              "skipped": false
            }
          ],
          "suites": [],
          "passes": [
            "bd42c36e-f3fb-431f-8158-dee43d36386d",
            "9073a53e-3f4c-4169-b97e-6c848d2a27b1"
          ],
          "failures": [],
          "pending": [],
          "skipped": [],
          "duration": 1236,
          "root": false,
          "rootEmpty": false,
          "_timeout": 2000
        }
      ],
      "passes": [],
      "failures": [],
      "pending": [],
      "skipped": [],
      "duration": 0,
      "root": true,
      "rootEmpty": true,
      "_timeout": 2000
    }
  ],
  "meta": {
    "mocha": {
      "version": "7.0.1"
    },
    "mochawesome": {
      "options": {
        "quiet": false,
        "reportFilename": "mochawesome",
        "saveHtml": false,
        "saveJson": true,
        "consoleReporter": "spec",
        "useInlineDiffs": false,
        "code": true
      },
      "version": "6.2.1"
    },
    "marge": {
      "options": {
        "reportDir": "raw_reports",
        "overwrite": false,
        "html": false,
        "json": true
      },
      "version": "5.1.0"
    }
  }
}